create_forwarder_dll/__init__.py
create_forwarder_dll/_version.py
create_forwarder_dll-0.10.dist-info/licenses/LICENSE
create_forwarder_dll-0.10.dist-info/METADATA
create_forwarder_dll-0.10.dist-info/WHEEL
create_forwarder_dll-0.10.dist-info/entry_points.txt
create_forwarder_dll-0.10.dist-info/top_level.txt
create_forwarder_dll-0.10.dist-info/RECORD
