Metadata-Version: 2.4
Name: create-forwarder-dll
Version: 0.10
Summary: Creates a DLL that forwards all the symbols to another DLL
Author-email: Isuru Fernando <isuruf@gmail.com>
License: BSD-3-Clause
Project-URL: repository, https://github.com/isuruf/create-forwarder-dll
Requires-Python: >=3
License-File: LICENSE
Requires-Dist: setuptools>=65
Dynamic: license-file
